panel_copy_paste/__init__.py
panel_copy_paste/_copy_button.py
panel_copy_paste/_paste_button.py
panel_copy_paste/main.py
panel_copy_paste/py.typed
panel_copy_paste-0.0.4.dist-info/METADATA
panel_copy_paste-0.0.4.dist-info/WHEEL
panel_copy_paste-0.0.4.dist-info/licenses/LICENSE.txt
panel_copy_paste-0.0.4.dist-info/RECORD
