Metadata-Version: 2.3
Name: panel-copy-paste
Version: 0.0.4
Summary: Extends HoloViz Panel with functionality to copy to and paste from the clipboard
Project-URL: Homepage, https://github.com/awesome-panel/panel-copy-paste
Project-URL: Source, https://github.com/awesome-panel/panel-copy-paste
Author-email: Marc Skov Madsen <marc.skov.madsen@gmail.com>
Maintainer-email: Marc Skov Madsen <marc.skov.madsen@gmail.com>
License: BSD
Classifier: Development Status :: 5 - Production/Stable
Classifier: Intended Audience :: Developers
Classifier: Intended Audience :: Science/Research
Classifier: License :: OSI Approved :: BSD License
Classifier: Natural Language :: English
Classifier: Operating System :: OS Independent
Classifier: Programming Language :: Python :: 3
Classifier: Programming Language :: Python :: 3.11
Classifier: Programming Language :: Python :: 3.12
Classifier: Programming Language :: Python :: 3.13
Classifier: Topic :: Scientific/Engineering
Classifier: Topic :: Software Development :: Libraries
Requires-Python: >=3.11
Requires-Dist: narwhals
Requires-Dist: packaging
Requires-Dist: panel>=1.5.0
Provides-Extra: dev
Requires-Dist: jedi-language-server; (sys_platform == 'linux') and extra == 'dev'
Requires-Dist: mkdocs; extra == 'dev'
Requires-Dist: mkdocs-material; extra == 'dev'
Requires-Dist: mkdocs-pycafe; extra == 'dev'
Requires-Dist: mkdocstrings[python]; extra == 'dev'
Requires-Dist: pandas; extra == 'dev'
Requires-Dist: polars; extra == 'dev'
Requires-Dist: pre-commit; extra == 'dev'
Requires-Dist: pytest; extra == 'dev'
Requires-Dist: pytest-asyncio; extra == 'dev'
Requires-Dist: pytest-rerunfailures; extra == 'dev'
Requires-Dist: pytest-xdist; extra == 'dev'
Requires-Dist: watchfiles; extra == 'dev'
Provides-Extra: mypy
Requires-Dist: mypy; extra == 'mypy'
Requires-Dist: types-requests; extra == 'mypy'
Requires-Dist: typing-extensions; extra == 'mypy'
